[
    {
        "name": "Hawk Republic",
        "data": [
            [
                1747440000000,
                55.10204081632652
            ],
            [
                1747526400000,
                47.26027397260274
            ],
            [
                1747612800000,
                44.29223744292237
            ],
            [
                1747699200000,
                42.42424242424242
            ],
            [
                1747785600000,
                41.97860962566845
            ],
            [
                1747872000000,
                43.45898004434589
            ],
            [
                1747958400000,
                43.462246777163905
            ],
            [
                1748044800000,
                43.5126582278481
            ],
            [
                1748131200000,
                43.42465753424658
            ],
            [
                1748217600000,
                43.90243902439025
            ],
            [
                1748304000000,
                43.12849162011173
            ],
            [
                1748390400000,
                43.020833333333336
            ],
            [
                1748476800000,
                42.80117531831537
            ],
            [
                1748563200000,
                43.315018315018314
            ],
            [
                1748649600000,
                43.11531841652324
            ],
            [
                1748736000000,
                43.32514332514332
            ],
            [
                1748822400000,
                43.82376081825334
            ],
            [
                1748908800000,
                44.26106526631658
            ],
            [
                1748995200000,
                44.612068965517246
            ],
            [
                1749081600000,
                44.872677219545764
            ],
            [
                1749168000000,
                44.89123269611074
            ],
            [
                1749254400000,
                45.10178117048346
            ],
            [
                1749340800000,
                44.92665036674816
            ],
            [
                1749427200000,
                44.67333725721012
            ],
            [
                1749513600000,
                44.50768355150825
            ],
            [
                1749600000000,
                44.04827207899068
            ],
            [
                1749686400000,
                43.78666666666667
            ],
            [
                1749772800000,
                43.45114345114345
            ],
            [
                1749859200000,
                42.857142857142854
            ],
            [
                1749945600000,
                42.72369714847591
            ],
            [
                1750032000000,
                42.589928057553955
            ],
            [
                1750118400000,
                42.612826603325416
            ]
        ],
        "matches": [
            [
                1747440000000,
                49
            ],
            [
                1747526400000,
                146
            ],
            [
                1747612800000,
                219
            ],
            [
                1747699200000,
                297
            ],
            [
                1747785600000,
                374
            ],
            [
                1747872000000,
                451
            ],
            [
                1747958400000,
                543
            ],
            [
                1748044800000,
                632
            ],
            [
                1748131200000,
                730
            ],
            [
                1748217600000,
                820
            ],
            [
                1748304000000,
                895
            ],
            [
                1748390400000,
                960
            ],
            [
                1748476800000,
                1021
            ],
            [
                1748563200000,
                1092
            ],
            [
                1748649600000,
                1162
            ],
            [
                1748736000000,
                1221
            ],
            [
                1748822400000,
                1271
            ],
            [
                1748908800000,
                1333
            ],
            [
                1748995200000,
                1392
            ],
            [
                1749081600000,
                1453
            ],
            [
                1749168000000,
                1517
            ],
            [
                1749254400000,
                1572
            ],
            [
                1749340800000,
                1636
            ],
            [
                1749427200000,
                1699
            ],
            [
                1749513600000,
                1757
            ],
            [
                1749600000000,
                1823
            ],
            [
                1749686400000,
                1875
            ],
            [
                1749772800000,
                1924
            ],
            [
                1749859200000,
                1974
            ],
            [
                1749945600000,
                2034
            ],
            [
                1750032000000,
                2085
            ],
            [
                1750118400000,
                2105
            ]
        ]
    },
    {
        "name": "Eagle Federation",
        "data": [
            [
                1747440000000,
                50
            ],
            [
                1747526400000,
                58.82352941176471
            ],
            [
                1747612800000,
                61.711711711711715
            ],
            [
                1747699200000,
                63.39869281045751
            ],
            [
                1747785600000,
                63.68286445012787
            ],
            [
                1747872000000,
                61.75213675213676
            ],
            [
                1747958400000,
                62.257495590828924
            ],
            [
                1748044800000,
                62.29260935143288
            ],
            [
                1748131200000,
                61.929595827900904
            ],
            [
                1748217600000,
                61.35040745052387
            ],
            [
                1748304000000,
                62.21985058697972
            ],
            [
                1748390400000,
                62.27544910179641
            ],
            [
                1748476800000,
                62.37064910630291
            ],
            [
                1748563200000,
                61.95939982347749
            ],
            [
                1748649600000,
                62.26101413133832
            ],
            [
                1748736000000,
                61.934972244250595
            ],
            [
                1748822400000,
                61.63234172387491
            ],
            [
                1748908800000,
                61.22004357298475
            ],
            [
                1748995200000,
                60.90592334494773
            ],
            [
                1749081600000,
                60.55962691538974
            ],
            [
                1749168000000,
                60.561582641991066
            ],
            [
                1749254400000,
                60.41923551171393
            ],
            [
                1749340800000,
                60.61502069781195
            ],
            [
                1749427200000,
                60.820045558086555
            ],
            [
                1749513600000,
                60.9366391184573
            ],
            [
                1749600000000,
                61.252653927813164
            ],
            [
                1749686400000,
                61.39989706639217
            ],
            [
                1749772800000,
                61.9
            ],
            [
                1749859200000,
                62.3718887262079
            ],
            [
                1749945600000,
                62.452651515151516
            ],
            [
                1750032000000,
                62.54041570438799
            ],
            [
                1750118400000,
                62.56855575868373
            ]
        ],
        "matches": [
            [
                1747440000000,
                48
            ],
            [
                1747526400000,
                153
            ],
            [
                1747612800000,
                222
            ],
            [
                1747699200000,
                306
            ],
            [
                1747785600000,
                391
            ],
            [
                1747872000000,
                468
            ],
            [
                1747958400000,
                567
            ],
            [
                1748044800000,
                663
            ],
            [
                1748131200000,
                767
            ],
            [
                1748217600000,
                859
            ],
            [
                1748304000000,
                937
            ],
            [
                1748390400000,
                1002
            ],
            [
                1748476800000,
                1063
            ],
            [
                1748563200000,
                1133
            ],
            [
                1748649600000,
                1203
            ],
            [
                1748736000000,
                1261
            ],
            [
                1748822400000,
                1311
            ],
            [
                1748908800000,
                1377
            ],
            [
                1748995200000,
                1435
            ],
            [
                1749081600000,
                1501
            ],
            [
                1749168000000,
                1567
            ],
            [
                1749254400000,
                1622
            ],
            [
                1749340800000,
                1691
            ],
            [
                1749427200000,
                1756
            ],
            [
                1749513600000,
                1815
            ],
            [
                1749600000000,
                1884
            ],
            [
                1749686400000,
                1943
            ],
            [
                1749772800000,
                2000
            ],
            [
                1749859200000,
                2049
            ],
            [
                1749945600000,
                2112
            ],
            [
                1750032000000,
                2165
            ],
            [
                1750118400000,
                2188
            ]
        ]
    },
    {
        "name": "FISH State",
        "data": [
            [
                1747440000000,
                0
            ],
            [
                1747526400000,
                0
            ],
            [
                1747612800000,
                6.451612903225806
            ],
            [
                1747699200000,
                4.878048780487805
            ],
            [
                1747785600000,
                5.660377358490567
            ],
            [
                1747872000000,
                5.263157894736842
            ],
            [
                1747958400000,
                5.263157894736842
            ],
            [
                1748044800000,
                6.451612903225806
            ],
            [
                1748131200000,
                7.766990291262135
            ],
            [
                1748217600000,
                7.207207207207207
            ],
            [
                1748304000000,
                7.936507936507936
            ],
            [
                1748390400000,
                8.208955223880597
            ],
            [
                1748476800000,
                7.971014492753622
            ],
            [
                1748563200000,
                8.053691275167784
            ],
            [
                1748649600000,
                7.547169811320755
            ],
            [
                1748736000000,
                8.433734939759036
            ],
            [
                1748822400000,
                7.954545454545454
            ],
            [
                1748908800000,
                8.064516129032258
            ],
            [
                1748995200000,
                8.205128205128204
            ],
            [
                1749081600000,
                8.823529411764707
            ],
            [
                1749168000000,
                8.878504672897195
            ],
            [
                1749254400000,
                8.558558558558559
            ],
            [
                1749340800000,
                8.583690987124463
            ],
            [
                1749427200000,
                8.71369294605809
            ],
            [
                1749513600000,
                9.2
            ],
            [
                1749600000000,
                9.090909090909092
            ],
            [
                1749686400000,
                9.615384615384617
            ],
            [
                1749772800000,
                9.420289855072465
            ],
            [
                1749859200000,
                9.9644128113879
            ],
            [
                1749945600000,
                9.79020979020979
            ],
            [
                1750032000000,
                9.931506849315069
            ],
            [
                1750118400000,
                9.764309764309765
            ]
        ],
        "matches": [
            [
                1747440000000,
                5
            ],
            [
                1747526400000,
                19
            ],
            [
                1747612800000,
                31
            ],
            [
                1747699200000,
                41
            ],
            [
                1747785600000,
                53
            ],
            [
                1747872000000,
                57
            ],
            [
                1747958400000,
                76
            ],
            [
                1748044800000,
                93
            ],
            [
                1748131200000,
                103
            ],
            [
                1748217600000,
                111
            ],
            [
                1748304000000,
                126
            ],
            [
                1748390400000,
                134
            ],
            [
                1748476800000,
                138
            ],
            [
                1748563200000,
                149
            ],
            [
                1748649600000,
                159
            ],
            [
                1748736000000,
                166
            ],
            [
                1748822400000,
                176
            ],
            [
                1748908800000,
                186
            ],
            [
                1748995200000,
                195
            ],
            [
                1749081600000,
                204
            ],
            [
                1749168000000,
                214
            ],
            [
                1749254400000,
                222
            ],
            [
                1749340800000,
                233
            ],
            [
                1749427200000,
                241
            ],
            [
                1749513600000,
                250
            ],
            [
                1749600000000,
                253
            ],
            [
                1749686400000,
                260
            ],
            [
                1749772800000,
                276
            ],
            [
                1749859200000,
                281
            ],
            [
                1749945600000,
                286
            ],
            [
                1750032000000,
                292
            ],
            [
                1750118400000,
                297
            ]
        ]
    }
]