[
    {
        "name": "Hawk Republic",
        "data": [
            [
                1747699200000,
                51.162790697674424
            ],
            [
                1747785600000,
                55.28455284552846
            ],
            [
                1747872000000,
                57.14285714285714
            ],
            [
                1747958400000,
                53.985507246376805
            ],
            [
                1748044800000,
                54.874651810584965
            ],
            [
                1748131200000,
                56.75057208237986
            ],
            [
                1748217600000,
                56.877323420074354
            ],
            [
                1748304000000,
                56.847133757961785
            ],
            [
                1748390400000,
                56.34588563458857
            ],
            [
                1748476800000,
                56.04938271604938
            ],
            [
                1748563200000,
                56.35964912280702
            ],
            [
                1748649600000,
                55.93719332679097
            ],
            [
                1748736000000,
                56.317689530685925
            ],
            [
                1748822400000,
                56.28691983122363
            ],
            [
                1748908800000,
                56.18597320724981
            ],
            [
                1748995200000,
                56.49303008070433
            ],
            [
                1749081600000,
                56.83701657458563
            ],
            [
                1749168000000,
                56.76567656765676
            ],
            [
                1749254400000,
                56.7313713212273
            ],
            [
                1749340800000,
                57.11733174508636
            ],
            [
                1749427200000,
                57.17552887364208
            ],
            [
                1749513600000,
                57.3170731707317
            ],
            [
                1749600000000,
                57.14285714285714
            ],
            [
                1749686400000,
                57.0385818561001
            ],
            [
                1749772800000,
                56.72930421533774
            ],
            [
                1749859200000,
                56.40900195694716
            ],
            [
                1749945600000,
                55.96199524940617
            ],
            [
                1750032000000,
                55.50945136007377
            ],
            [
                1750118400000,
                55.305755395683455
            ],
            [
                1750204800000,
                55.07436570428696
            ],
            [
                1750291200000,
                54.851063829787236
            ],
            [
                1750377600000,
                54.629629629629626
            ]
        ],
        "matches": [
            [
                1747699200000,
                43
            ],
            [
                1747785600000,
                123
            ],
            [
                1747872000000,
                196
            ],
            [
                1747958400000,
                276
            ],
            [
                1748044800000,
                359
            ],
            [
                1748131200000,
                437
            ],
            [
                1748217600000,
                538
            ],
            [
                1748304000000,
                628
            ],
            [
                1748390400000,
                717
            ],
            [
                1748476800000,
                810
            ],
            [
                1748563200000,
                912
            ],
            [
                1748649600000,
                1019
            ],
            [
                1748736000000,
                1108
            ],
            [
                1748822400000,
                1185
            ],
            [
                1748908800000,
                1269
            ],
            [
                1748995200000,
                1363
            ],
            [
                1749081600000,
                1448
            ],
            [
                1749168000000,
                1515
            ],
            [
                1749254400000,
                1597
            ],
            [
                1749340800000,
                1679
            ],
            [
                1749427200000,
                1749
            ],
            [
                1749513600000,
                1804
            ],
            [
                1749600000000,
                1862
            ],
            [
                1749686400000,
                1918
            ],
            [
                1749772800000,
                1969
            ],
            [
                1749859200000,
                2044
            ],
            [
                1749945600000,
                2105
            ],
            [
                1750032000000,
                2169
            ],
            [
                1750118400000,
                2224
            ],
            [
                1750204800000,
                2286
            ],
            [
                1750291200000,
                2350
            ],
            [
                1750377600000,
                2376
            ]
        ]
    },
    {
        "name": "Eagle Federation",
        "data": [
            [
                1747699200000,
                48.837209302325576
            ],
            [
                1747785600000,
                44.71544715447154
            ],
            [
                1747872000000,
                42.857142857142854
            ],
            [
                1747958400000,
                46.01449275362319
            ],
            [
                1748044800000,
                45.12534818941504
            ],
            [
                1748131200000,
                43.24942791762014
            ],
            [
                1748217600000,
                43.12267657992565
            ],
            [
                1748304000000,
                43.152866242038215
            ],
            [
                1748390400000,
                43.65411436541143
            ],
            [
                1748476800000,
                43.95061728395061
            ],
            [
                1748563200000,
                43.640350877192986
            ],
            [
                1748649600000,
                44.062806673209025
            ],
            [
                1748736000000,
                43.682310469314075
            ],
            [
                1748822400000,
                43.71308016877637
            ],
            [
                1748908800000,
                43.8140267927502
            ],
            [
                1748995200000,
                43.50696991929567
            ],
            [
                1749081600000,
                43.16298342541437
            ],
            [
                1749168000000,
                43.23432343234324
            ],
            [
                1749254400000,
                43.2686286787727
            ],
            [
                1749340800000,
                42.88266825491364
            ],
            [
                1749427200000,
                42.82447112635792
            ],
            [
                1749513600000,
                42.68292682926829
            ],
            [
                1749600000000,
                42.857142857142854
            ],
            [
                1749686400000,
                42.96141814389989
            ],
            [
                1749772800000,
                43.270695784662266
            ],
            [
                1749859200000,
                43.590998043052835
            ],
            [
                1749945600000,
                44.03800475059382
            ],
            [
                1750032000000,
                44.49054863992623
            ],
            [
                1750118400000,
                44.694244604316545
            ],
            [
                1750204800000,
                44.92563429571304
            ],
            [
                1750291200000,
                45.148936170212764
            ],
            [
                1750377600000,
                45.370370370370374
            ]
        ],
        "matches": [
            [
                1747699200000,
                43
            ],
            [
                1747785600000,
                123
            ],
            [
                1747872000000,
                196
            ],
            [
                1747958400000,
                276
            ],
            [
                1748044800000,
                359
            ],
            [
                1748131200000,
                437
            ],
            [
                1748217600000,
                538
            ],
            [
                1748304000000,
                628
            ],
            [
                1748390400000,
                717
            ],
            [
                1748476800000,
                810
            ],
            [
                1748563200000,
                912
            ],
            [
                1748649600000,
                1019
            ],
            [
                1748736000000,
                1108
            ],
            [
                1748822400000,
                1185
            ],
            [
                1748908800000,
                1269
            ],
            [
                1748995200000,
                1363
            ],
            [
                1749081600000,
                1448
            ],
            [
                1749168000000,
                1515
            ],
            [
                1749254400000,
                1597
            ],
            [
                1749340800000,
                1679
            ],
            [
                1749427200000,
                1749
            ],
            [
                1749513600000,
                1804
            ],
            [
                1749600000000,
                1862
            ],
            [
                1749686400000,
                1918
            ],
            [
                1749772800000,
                1969
            ],
            [
                1749859200000,
                2044
            ],
            [
                1749945600000,
                2105
            ],
            [
                1750032000000,
                2169
            ],
            [
                1750118400000,
                2224
            ],
            [
                1750204800000,
                2286
            ],
            [
                1750291200000,
                2350
            ],
            [
                1750377600000,
                2376
            ]
        ]
    }
]