[
    {
        "name": "Eagle Federation",
        "data": [
            [
                1747699200000,
                20
            ],
            [
                1747785600000,
                27.27272727272727
            ],
            [
                1747872000000,
                35.483870967741936
            ],
            [
                1747958400000,
                41.48936170212766
            ],
            [
                1748044800000,
                37.69230769230769
            ],
            [
                1748131200000,
                42.10526315789473
            ],
            [
                1748217600000,
                43.61233480176212
            ],
            [
                1748304000000,
                42.238267148014444
            ],
            [
                1748390400000,
                41.98717948717949
            ],
            [
                1748476800000,
                41.07648725212464
            ],
            [
                1748563200000,
                40.05102040816326
            ],
            [
                1748649600000,
                39.189189189189186
            ],
            [
                1748736000000,
                39.166666666666664
            ],
            [
                1748822400000,
                39.029126213592235
            ],
            [
                1748908800000,
                38.30570902394107
            ],
            [
                1748995200000,
                38.095238095238095
            ],
            [
                1749081600000,
                38.11965811965812
            ],
            [
                1749168000000,
                37.5
            ],
            [
                1749254400000,
                36.93693693693694
            ],
            [
                1749340800000,
                36.637931034482754
            ],
            [
                1749427200000,
                36.84210526315789
            ],
            [
                1749513600000,
                36.51006711409396
            ],
            [
                1749600000000,
                36.340206185567006
            ],
            [
                1749686400000,
                36.39751552795031
            ],
            [
                1749772800000,
                36.22327790973871
            ],
            [
                1749859200000,
                35.900339750849376
            ],
            [
                1749945600000,
                35.714285714285715
            ],
            [
                1750032000000,
                35.91101694915254
            ],
            [
                1750118400000,
                35.51020408163265
            ],
            [
                1750204800000,
                35.756972111553786
            ],
            [
                1750291200000,
                35.88007736943907
            ],
            [
                1750377600000,
                35.693779904306226
            ]
        ],
        "matches": [
            [
                1747699200000,
                15
            ],
            [
                1747785600000,
                44
            ],
            [
                1747872000000,
                62
            ],
            [
                1747958400000,
                94
            ],
            [
                1748044800000,
                130
            ],
            [
                1748131200000,
                171
            ],
            [
                1748217600000,
                227
            ],
            [
                1748304000000,
                277
            ],
            [
                1748390400000,
                312
            ],
            [
                1748476800000,
                353
            ],
            [
                1748563200000,
                392
            ],
            [
                1748649600000,
                444
            ],
            [
                1748736000000,
                480
            ],
            [
                1748822400000,
                515
            ],
            [
                1748908800000,
                543
            ],
            [
                1748995200000,
                567
            ],
            [
                1749081600000,
                585
            ],
            [
                1749168000000,
                624
            ],
            [
                1749254400000,
                666
            ],
            [
                1749340800000,
                696
            ],
            [
                1749427200000,
                722
            ],
            [
                1749513600000,
                745
            ],
            [
                1749600000000,
                776
            ],
            [
                1749686400000,
                805
            ],
            [
                1749772800000,
                842
            ],
            [
                1749859200000,
                883
            ],
            [
                1749945600000,
                924
            ],
            [
                1750032000000,
                944
            ],
            [
                1750118400000,
                980
            ],
            [
                1750204800000,
                1004
            ],
            [
                1750291200000,
                1034
            ],
            [
                1750377600000,
                1045
            ]
        ]
    },
    {
        "name": "Schwalbenheim Kingdom",
        "data": [
            [
                1747699200000,
                62.5
            ],
            [
                1747785600000,
                57.608695652173914
            ],
            [
                1747872000000,
                51.67785234899329
            ],
            [
                1747958400000,
                48.86877828054298
            ],
            [
                1748044800000,
                49.30555555555556
            ],
            [
                1748131200000,
                47.20670391061452
            ],
            [
                1748217600000,
                45.01108647450111
            ],
            [
                1748304000000,
                44.81481481481481
            ],
            [
                1748390400000,
                43.01412872841444
            ],
            [
                1748476800000,
                42.582417582417584
            ],
            [
                1748563200000,
                44.019728729963006
            ],
            [
                1748649600000,
                44.97816593886463
            ],
            [
                1748736000000,
                45.58969276511397
            ],
            [
                1748822400000,
                45.91368227731864
            ],
            [
                1748908800000,
                46.53979238754326
            ],
            [
                1748995200000,
                46.513535684987694
            ],
            [
                1749081600000,
                46.650906225374314
            ],
            [
                1749168000000,
                47.072072072072075
            ],
            [
                1749254400000,
                47.008547008547005
            ],
            [
                1749340800000,
                46.55290102389078
            ],
            [
                1749427200000,
                46.60961158657011
            ],
            [
                1749513600000,
                46.57270980140935
            ],
            [
                1749600000000,
                46.51019147621989
            ],
            [
                1749686400000,
                46.144721233689204
            ],
            [
                1749772800000,
                46.114285714285714
            ],
            [
                1749859200000,
                46.10318331503842
            ],
            [
                1749945600000,
                45.97457627118644
            ],
            [
                1750032000000,
                45.73643410852713
            ],
            [
                1750118400000,
                45.9
            ],
            [
                1750204800000,
                45.683802133850634
            ],
            [
                1750291200000,
                45.70754716981132
            ],
            [
                1750377600000,
                45.68362109192721
            ]
        ],
        "matches": [
            [
                1747699200000,
                32
            ],
            [
                1747785600000,
                92
            ],
            [
                1747872000000,
                149
            ],
            [
                1747958400000,
                221
            ],
            [
                1748044800000,
                288
            ],
            [
                1748131200000,
                358
            ],
            [
                1748217600000,
                451
            ],
            [
                1748304000000,
                540
            ],
            [
                1748390400000,
                637
            ],
            [
                1748476800000,
                728
            ],
            [
                1748563200000,
                811
            ],
            [
                1748649600000,
                916
            ],
            [
                1748736000000,
                1009
            ],
            [
                1748822400000,
                1089
            ],
            [
                1748908800000,
                1156
            ],
            [
                1748995200000,
                1219
            ],
            [
                1749081600000,
                1269
            ],
            [
                1749168000000,
                1332
            ],
            [
                1749254400000,
                1404
            ],
            [
                1749340800000,
                1465
            ],
            [
                1749427200000,
                1519
            ],
            [
                1749513600000,
                1561
            ],
            [
                1749600000000,
                1619
            ],
            [
                1749686400000,
                1686
            ],
            [
                1749772800000,
                1750
            ],
            [
                1749859200000,
                1822
            ],
            [
                1749945600000,
                1888
            ],
            [
                1750032000000,
                1935
            ],
            [
                1750118400000,
                2000
            ],
            [
                1750204800000,
                2062
            ],
            [
                1750291200000,
                2120
            ],
            [
                1750377600000,
                2143
            ]
        ]
    },
    {
        "name": "Hawk Republic",
        "data": [
            [
                1747699200000,
                52.17391304347826
            ],
            [
                1747785600000,
                54.83870967741935
            ],
            [
                1747872000000,
                56.074766355140184
            ],
            [
                1747958400000,
                56.52173913043478
            ],
            [
                1748044800000,
                58.57142857142858
            ],
            [
                1748131200000,
                59.21568627450981
            ],
            [
                1748217600000,
                61.70886075949367
            ],
            [
                1748304000000,
                63.12997347480106
            ],
            [
                1748390400000,
                65.34216335540839
            ],
            [
                1748476800000,
                66.41074856046065
            ],
            [
                1748563200000,
                64.80541455160744
            ],
            [
                1748649600000,
                64.11411411411412
            ],
            [
                1748736000000,
                63.022941970310384
            ],
            [
                1748822400000,
                62.56218905472637
            ],
            [
                1748908800000,
                62.19081272084806
            ],
            [
                1748995200000,
                62.24944320712695
            ],
            [
                1749081600000,
                61.86440677966102
            ],
            [
                1749168000000,
                61.8421052631579
            ],
            [
                1749254400000,
                62.38003838771593
            ],
            [
                1749340800000,
                63.081130355515036
            ],
            [
                1749427200000,
                62.907488986784145
            ],
            [
                1749513600000,
                63.16239316239316
            ],
            [
                1749600000000,
                63.308763308763304
            ],
            [
                1749686400000,
                63.68627450980392
            ],
            [
                1749772800000,
                63.93939393939394
            ],
            [
                1749859200000,
                64.21818181818182
            ],
            [
                1749945600000,
                64.66854724964739
            ],
            [
                1750032000000,
                64.85182632667126
            ],
            [
                1750118400000,
                65.01340482573727
            ],
            [
                1750204800000,
                65.02590673575129
            ],
            [
                1750291200000,
                64.92443324937027
            ],
            [
                1750377600000,
                65.08728179551122
            ]
        ],
        "matches": [
            [
                1747699200000,
                23
            ],
            [
                1747785600000,
                62
            ],
            [
                1747872000000,
                107
            ],
            [
                1747958400000,
                161
            ],
            [
                1748044800000,
                210
            ],
            [
                1748131200000,
                255
            ],
            [
                1748217600000,
                316
            ],
            [
                1748304000000,
                377
            ],
            [
                1748390400000,
                453
            ],
            [
                1748476800000,
                521
            ],
            [
                1748563200000,
                591
            ],
            [
                1748649600000,
                666
            ],
            [
                1748736000000,
                741
            ],
            [
                1748822400000,
                804
            ],
            [
                1748908800000,
                849
            ],
            [
                1748995200000,
                898
            ],
            [
                1749081600000,
                944
            ],
            [
                1749168000000,
                988
            ],
            [
                1749254400000,
                1042
            ],
            [
                1749340800000,
                1097
            ],
            [
                1749427200000,
                1135
            ],
            [
                1749513600000,
                1170
            ],
            [
                1749600000000,
                1221
            ],
            [
                1749686400000,
                1275
            ],
            [
                1749772800000,
                1320
            ],
            [
                1749859200000,
                1375
            ],
            [
                1749945600000,
                1418
            ],
            [
                1750032000000,
                1451
            ],
            [
                1750118400000,
                1492
            ],
            [
                1750204800000,
                1544
            ],
            [
                1750291200000,
                1588
            ],
            [
                1750377600000,
                1604
            ]
        ]
    }
]