[
    {
        "name": "Hawk Republic",
        "data": [
            [
                1747267200000,
                36.17021276595745
            ],
            [
                1747353600000,
                36.0655737704918
            ],
            [
                1747440000000,
                40.63926940639269
            ],
            [
                1747526400000,
                40.993788819875775
            ],
            [
                1747612800000,
                41.20734908136483
            ],
            [
                1747699200000,
                41.8141592920354
            ],
            [
                1747785600000,
                41.58790170132325
            ],
            [
                1747872000000,
                41.70771756978653
            ],
            [
                1747958400000,
                41.41414141414141
            ],
            [
                1748044800000,
                40.76433121019109
            ],
            [
                1748131200000,
                40.702947845804985
            ],
            [
                1748217600000,
                40.668824163969795
            ],
            [
                1748304000000,
                40.67278287461774
            ],
            [
                1748390400000,
                40.32723772858518
            ],
            [
                1748476800000,
                40.550458715596335
            ],
            [
                1748563200000,
                41.104294478527606
            ],
            [
                1748649600000,
                41.86822351959967
            ],
            [
                1748736000000,
                42.03362690152122
            ],
            [
                1748822400000,
                42.12144504227518
            ],
            [
                1748908800000,
                41.71597633136095
            ],
            [
                1748995200000,
                41.89864382583869
            ],
            [
                1749081600000,
                42.2680412371134
            ],
            [
                1749168000000,
                42.6
            ],
            [
                1749254400000,
                42.37179487179487
            ],
            [
                1749340800000,
                42.71481942714819
            ],
            [
                1749427200000,
                42.18181818181818
            ],
            [
                1749513600000,
                42.09288653733098
            ],
            [
                1749600000000,
                41.891117478510026
            ],
            [
                1749686400000,
                42.07865168539326
            ],
            [
                1749772800000,
                41.903719912472646
            ],
            [
                1749859200000,
                41.98717948717949
            ],
            [
                1749945600000,
                41.64470216130733
            ]
        ],
        "matches": [
            [
                1747267200000,
                47
            ],
            [
                1747353600000,
                122
            ],
            [
                1747440000000,
                219
            ],
            [
                1747526400000,
                322
            ],
            [
                1747612800000,
                381
            ],
            [
                1747699200000,
                452
            ],
            [
                1747785600000,
                529
            ],
            [
                1747872000000,
                609
            ],
            [
                1747958400000,
                693
            ],
            [
                1748044800000,
                785
            ],
            [
                1748131200000,
                882
            ],
            [
                1748217600000,
                927
            ],
            [
                1748304000000,
                981
            ],
            [
                1748390400000,
                1039
            ],
            [
                1748476800000,
                1090
            ],
            [
                1748563200000,
                1141
            ],
            [
                1748649600000,
                1199
            ],
            [
                1748736000000,
                1249
            ],
            [
                1748822400000,
                1301
            ],
            [
                1748908800000,
                1352
            ],
            [
                1748995200000,
                1401
            ],
            [
                1749081600000,
                1455
            ],
            [
                1749168000000,
                1500
            ],
            [
                1749254400000,
                1560
            ],
            [
                1749340800000,
                1606
            ],
            [
                1749427200000,
                1650
            ],
            [
                1749513600000,
                1701
            ],
            [
                1749600000000,
                1745
            ],
            [
                1749686400000,
                1780
            ],
            [
                1749772800000,
                1828
            ],
            [
                1749859200000,
                1872
            ],
            [
                1749945600000,
                1897
            ]
        ]
    },
    {
        "name": "Eagle Federation",
        "data": [
            [
                1747267200000,
                67.9245283018868
            ],
            [
                1747353600000,
                67.66917293233082
            ],
            [
                1747440000000,
                63.63636363636363
            ],
            [
                1747526400000,
                63.55685131195335
            ],
            [
                1747612800000,
                63.503649635036496
            ],
            [
                1747699200000,
                63.190184049079754
            ],
            [
                1747785600000,
                63.620386643233736
            ],
            [
                1747872000000,
                63.67851622874807
            ],
            [
                1747958400000,
                64.07103825136612
            ],
            [
                1748044800000,
                64.57831325301204
            ],
            [
                1748131200000,
                64.3850267379679
            ],
            [
                1748217600000,
                64.42405708460754
            ],
            [
                1748304000000,
                64.32015429122468
            ],
            [
                1748390400000,
                64.59854014598541
            ],
            [
                1748476800000,
                64.18039895923677
            ],
            [
                1748563200000,
                63.69691923397169
            ],
            [
                1748649600000,
                63.04520222045995
            ],
            [
                1748736000000,
                62.824427480916036
            ],
            [
                1748822400000,
                62.86764705882353
            ],
            [
                1748908800000,
                63.10198300283286
            ],
            [
                1748995200000,
                62.86689419795222
            ],
            [
                1749081600000,
                62.47531270572745
            ],
            [
                1749168000000,
                62.10862619808307
            ],
            [
                1749254400000,
                62.315270935960584
            ],
            [
                1749340800000,
                61.90191387559809
            ],
            [
                1749427200000,
                62.354312354312356
            ],
            [
                1749513600000,
                62.44343891402715
            ],
            [
                1749600000000,
                62.52063841496973
            ],
            [
                1749686400000,
                62.405609492988134
            ],
            [
                1749772800000,
                62.618296529968454
            ],
            [
                1749859200000,
                62.42952332137366
            ],
            [
                1749945600000,
                62.74014155712842
            ]
        ],
        "matches": [
            [
                1747267200000,
                53
            ],
            [
                1747353600000,
                133
            ],
            [
                1747440000000,
                231
            ],
            [
                1747526400000,
                343
            ],
            [
                1747612800000,
                411
            ],
            [
                1747699200000,
                489
            ],
            [
                1747785600000,
                569
            ],
            [
                1747872000000,
                647
            ],
            [
                1747958400000,
                732
            ],
            [
                1748044800000,
                830
            ],
            [
                1748131200000,
                935
            ],
            [
                1748217600000,
                981
            ],
            [
                1748304000000,
                1037
            ],
            [
                1748390400000,
                1096
            ],
            [
                1748476800000,
                1153
            ],
            [
                1748563200000,
                1201
            ],
            [
                1748649600000,
                1261
            ],
            [
                1748736000000,
                1310
            ],
            [
                1748822400000,
                1360
            ],
            [
                1748908800000,
                1412
            ],
            [
                1748995200000,
                1465
            ],
            [
                1749081600000,
                1519
            ],
            [
                1749168000000,
                1565
            ],
            [
                1749254400000,
                1624
            ],
            [
                1749340800000,
                1672
            ],
            [
                1749427200000,
                1716
            ],
            [
                1749513600000,
                1768
            ],
            [
                1749600000000,
                1817
            ],
            [
                1749686400000,
                1854
            ],
            [
                1749772800000,
                1902
            ],
            [
                1749859200000,
                1951
            ],
            [
                1749945600000,
                1978
            ]
        ]
    },
    {
        "name": "FISH State",
        "data": [
            [
                1747267200000,
                0
            ],
            [
                1747353600000,
                0
            ],
            [
                1747440000000,
                4.166666666666666
            ],
            [
                1747526400000,
                5.128205128205128
            ],
            [
                1747612800000,
                4.166666666666666
            ],
            [
                1747699200000,
                6.349206349206349
            ],
            [
                1747785600000,
                5.405405405405405
            ],
            [
                1747872000000,
                6.8181818181818175
            ],
            [
                1747958400000,
                6.0606060606060606
            ],
            [
                1748044800000,
                7.82608695652174
            ],
            [
                1748131200000,
                8.661417322834646
            ],
            [
                1748217600000,
                8.333333333333332
            ],
            [
                1748304000000,
                8.695652173913043
            ],
            [
                1748390400000,
                8.391608391608392
            ],
            [
                1748476800000,
                9.395973154362416
            ],
            [
                1748563200000,
                9.090909090909092
            ],
            [
                1748649600000,
                9.146341463414634
            ],
            [
                1748736000000,
                8.982035928143713
            ],
            [
                1748822400000,
                8.571428571428571
            ],
            [
                1748908800000,
                8.98876404494382
            ],
            [
                1748995200000,
                8.791208791208792
            ],
            [
                1749081600000,
                9.473684210526317
            ],
            [
                1749168000000,
                9.32642487046632
            ],
            [
                1749254400000,
                9.090909090909092
            ],
            [
                1749340800000,
                9.405940594059405
            ],
            [
                1749427200000,
                9.70873786407767
            ],
            [
                1749513600000,
                9.47867298578199
            ],
            [
                1749600000000,
                10.550458715596331
            ],
            [
                1749686400000,
                10.267857142857142
            ],
            [
                1749772800000,
                10
            ],
            [
                1749859200000,
                10.970464135021098
            ],
            [
                1749945600000,
                10.87866108786611
            ]
        ],
        "matches": [
            [
                1747267200000,
                6
            ],
            [
                1747353600000,
                13
            ],
            [
                1747440000000,
                24
            ],
            [
                1747526400000,
                39
            ],
            [
                1747612800000,
                48
            ],
            [
                1747699200000,
                63
            ],
            [
                1747785600000,
                74
            ],
            [
                1747872000000,
                88
            ],
            [
                1747958400000,
                99
            ],
            [
                1748044800000,
                115
            ],
            [
                1748131200000,
                127
            ],
            [
                1748217600000,
                132
            ],
            [
                1748304000000,
                138
            ],
            [
                1748390400000,
                143
            ],
            [
                1748476800000,
                149
            ],
            [
                1748563200000,
                154
            ],
            [
                1748649600000,
                164
            ],
            [
                1748736000000,
                167
            ],
            [
                1748822400000,
                175
            ],
            [
                1748908800000,
                178
            ],
            [
                1748995200000,
                182
            ],
            [
                1749081600000,
                190
            ],
            [
                1749168000000,
                193
            ],
            [
                1749254400000,
                198
            ],
            [
                1749340800000,
                202
            ],
            [
                1749427200000,
                206
            ],
            [
                1749513600000,
                211
            ],
            [
                1749600000000,
                218
            ],
            [
                1749686400000,
                224
            ],
            [
                1749772800000,
                230
            ],
            [
                1749859200000,
                237
            ],
            [
                1749945600000,
                239
            ]
        ]
    }
]